{
  "data": [
    {
      "id": "MDEwOlJlcG9zaXRvcnkyNDU0NjcyNzQ=",
      "name": "E-Commerce Products for your pets",
      "createdAt": "2020-03-06T16:26:54Z",
      "url": "https://github.com/JoelGalvez20/PF_VET",
      "description": "🔥 It's a E-Commerce where the loaged user can buy some products, which can be food, cages, shampoo, and others.",
      "isFork": false,
      "languages": [
        {
          "name": "HTML",
          "iconifyClass": "logos-html-5"
        },
        {
          "name": "CSS",
          "iconifyClass": "logos-css-3"
        },
        {
          "name": "JavaScript",
          "iconifyClass": "logos-javascript"
        },
        {"name":"React",
         "iconifyClass":"logos-react"}
      ]
    }
  ]
}
